xchtools/.env.example
xchtools/__init__.py
xchtools/algo/ac.py
xchtools/common.py
xchtools/connections.py
xchtools/funcflow.py
xchtools/logger.py
xchtools/settings.toml.example
xchtools-0.1.15.dist-info/METADATA
xchtools-0.1.15.dist-info/WHEEL
xchtools-0.1.15.dist-info/RECORD
